lisskins_api/__init__.py
lisskins_api/lisskins_api.py
lisskins_api-0.1.4.dist-info/LICENSE
lisskins_api-0.1.4.dist-info/METADATA
lisskins_api-0.1.4.dist-info/WHEEL
lisskins_api-0.1.4.dist-info/top_level.txt
lisskins_api-0.1.4.dist-info/RECORD
