Metadata-Version: 2.1
Name: lisskins-api
Version: 0.1.4
Summary: Module for interacting with Lis Skins API
Home-page: UNKNOWN
Author: $10,000 Lincoln Continental
License: UNKNOWN
Platform: UNKNOWN
License-File: LICENSE
Requires-Dist: aiohttp
